pyproject_devenv/__init__.py
pyproject_devenv/__main__.py
pyproject_devenv/config.py
pyproject_devenv/py.typed
pyproject_devenv-0.2.0.dist-info/LICENSE
pyproject_devenv-0.2.0.dist-info/METADATA
pyproject_devenv-0.2.0.dist-info/WHEEL
pyproject_devenv-0.2.0.dist-info/entry_points.txt
pyproject_devenv-0.2.0.dist-info/RECORD
