Metadata-Version: 2.2
Name: pyproject-devenv
Version: 0.2.0
Summary: Create virtual environments using pyproject.toml metadata.
Author-email: Dominic Davis-Foster <dominic@davis-foster.co.uk>
License: MIT
Keywords: pyproject,toml,virtualenv
Home-page: https://github.com/repo-helper/pyproject-devenv
Project-URL: Issue Tracker, https://github.com/repo-helper/pyproject-devenv/issues
Project-URL: Source Code, https://github.com/repo-helper/pyproject-devenv
Project-URL: Documentation, https://pyproject-devenv.readthedocs.io/en/latest
Platform: Windows
Platform: macOS
Platform: Linux
Classifier: Development Status :: 4 - Beta
Classifier: Environment :: Console
Classifier: Intended Audience :: Developers
Classifier: License :: OSI Approved :: MIT License
Classifier: Operating System :: OS Independent
Classifier: Programming Language :: Python
Classifier: Programming Language :: Python :: 3 :: Only
Classifier: Programming Language :: Python :: 3.7
Classifier: Programming Language :: Python :: 3.8
Classifier: Programming Language :: Python :: 3.9
Classifier: Programming Language :: Python :: 3.10
Classifier: Programming Language :: Python :: 3.11
Classifier: Programming Language :: Python :: 3.12
Classifier: Programming Language :: Python :: 3.13
Classifier: Programming Language :: Python :: Implementation :: CPython
Classifier: Programming Language :: Python :: Implementation :: PyPy
Classifier: Topic :: System :: Archiving :: Packaging
Classifier: Typing :: Typed
Requires-Python: >=3.7
Requires-Dist: click>=7.1.2
Requires-Dist: consolekit>=1.2.0
Requires-Dist: dom-toml>=0.4.0
Requires-Dist: domdf-python-tools>=2.9.0
Requires-Dist: packaging>=20.9
Requires-Dist: pyproject-parser>=0.2.0
Requires-Dist: shippinglabel>=0.14.1
Requires-Dist: typing-extensions>=3.7.4.3
Requires-Dist: virtualenv>=20.10.0
